{
  "last_update": "2026-02-20",
  "base_url": "https://drive.google.com/uc?export=download&id=",
  "files": [
    {
      "title": "االلغة الانجليزية - نماذج جديدة و اسئلة مكررة",
      "encrypted_filename": "x9O6B5_E_O_oYqEglZV.nPn",
      "id": "1jv0Zd2QojqZV7c9FRghMgKsBqryBhcVr",
      "category": "english"
    },
    {
      "title": "اللغة الانجليزية - قواعد",
      "encrypted_filename": "dbEMF8_E_G_J8740Xpl.nPn",
      "id": "1nejnUKPpKNWTR6DumG7nF8fCYR9Qedt5",
      "category": "english"
    },
    {
      "title": "الحاسوب - المنهج المثالي للامتحان الوطني",
      "encrypted_filename": "C5UlUmr_C_B_t7awy5z.nPn",
      "id": "1hpb3GJWOPXUxztE-K7FFBPVTtY6eL5Yv",
      "category": "computer"
    },
    {
      "title": "الحاسوب - نماذج جديدة و اسئلة مكررة",
      "encrypted_filename": "TAG8wm_C_O_aWu152hZ.nPn",
      "id": "10ycibEvjZ7Q-y9e5M1nweoHGrZZBipVV",
      "category": "computer"
    },
    {
      "title": "اللغة العربية - المنهج المثالي للامتحان الوطني",
      "encrypted_filename": "j5i8E8_A_G_Qeicyzqc.nPn",
      "id": "1Ua4zzSnKO8AjBA5Z48vIhbOp8TXzdbj3",
      "category": "arabic"
    },
    {
      "title": "اللغة العربية - نماذج جديدة و اسئلة مكررة",
      "encrypted_filename": "bu2FvdC_A_O_G03ZjKn.nPn",
      "id": "1Te9EYAuZaZVMTyZrB9AdofaOOo9-c8vS",
      "category": "arabic"
    },
    {
      "title": "اللغة الانجليزية - مرجع للامتحان الوطني",
      "encrypted_filename": "27SM8_E_O_BtfTmLeT9.nPn",
      "id": "1HLA-9g6GIr5xCH35jPtbJC2MIktBlde1",
      "category": "english"
    }
  ]
}
